deta_discord_interactions/__init__.py
deta_discord_interactions/client.py
deta_discord_interactions/command.py
deta_discord_interactions/context.py
deta_discord_interactions/discord.py
deta_discord_interactions/http.py
deta_discord_interactions/enums/__init__.py
deta_discord_interactions/enums/permissions.py
deta_discord_interactions/enums/response_types.py
deta_discord_interactions/models/__init__.py
deta_discord_interactions/models/attachment.py
deta_discord_interactions/models/autocomplete.py
deta_discord_interactions/models/channel.py
deta_discord_interactions/models/command.py
deta_discord_interactions/models/component.py
deta_discord_interactions/models/embed.py
deta_discord_interactions/models/interaction.py
deta_discord_interactions/models/message.py
deta_discord_interactions/models/modal.py
deta_discord_interactions/models/option.py
deta_discord_interactions/models/permission.py
deta_discord_interactions/models/role.py
deta_discord_interactions/models/user.py
deta_discord_interactions/models/utils.py
deta_discord_interactions/tests/__init__.py
deta_discord_interactions/tests/conftest.py
deta_discord_interactions/tests/test_command.py
deta_discord_interactions/tests/test_component.py
deta_discord_interactions/tests/test_context.py
deta_discord_interactions/tests/test_database.py
deta_discord_interactions/tests/test_drive.py
deta_discord_interactions/tests/test_handler.py
deta_discord_interactions/tests/test_http.py
deta_discord_interactions/tests/test_oauth.py
deta_discord_interactions/tests/test_options.py
deta_discord_interactions/tests/test_ping.py
deta_discord_interactions/tests/test_register.py
deta_discord_interactions/tests/test_response.py
deta_discord_interactions/tests/test_subcommand.py
deta_discord_interactions/tests/test_wsgi.py
deta_discord_interactions/utils/__init__.py
deta_discord_interactions/utils/cooldown/__init__.py
deta_discord_interactions/utils/database/__init__.py
deta_discord_interactions/utils/database/_local_base.py
deta_discord_interactions-0.1.1.dist-info/LICENSE
deta_discord_interactions-0.1.1.dist-info/METADATA
deta_discord_interactions-0.1.1.dist-info/WHEEL
deta_discord_interactions-0.1.1.dist-info/top_level.txt
deta_discord_interactions-0.1.1.dist-info/RECORD
