Metadata-Version: 2.1
Name: deta-discord-interactions
Version: 0.1.1
Summary: A web framework for Discord interactions specialized for usage in https://deta.sh
Home-page: https://github.com/etrotta/flask-discord-interactions/tree/deta
Author: etrotta
Author-email: etrotta <etrotta@duck.com>
License: MIT
Project-URL: Homepage, https://github.com/etrotta/flask-discord-interactions/tree/deta
Project-URL: Bug Tracker, https://github.com/etrotta/flask-discord-interactions/issues
Platform: any
Classifier: Programming Language :: Python :: 3
Classifier: License :: OSI Approved :: MIT License
Classifier: Operating System :: OS Independent
Requires-Python: >=3.9
License-File: LICENSE
Requires-Dist: requests
Requires-Dist: PyNaCl
Requires-Dist: requests-toolbelt
Requires-Dist: deta
